thirawat_mapper/__init__.py
thirawat_mapper/__main__.py
thirawat_mapper/cli.py
thirawat_mapper/index/__init__.py
thirawat_mapper/index/build.py
thirawat_mapper/infer/__init__.py
thirawat_mapper/infer/bulk.py
thirawat_mapper/infer/conversion.py
thirawat_mapper/infer/query.py
thirawat_mapper/infer/shared_filters.py
thirawat_mapper/infer/utils.py
thirawat_mapper/io/__init__.py
thirawat_mapper/io/duckdb_read.py
thirawat_mapper/io/export_csv.py
thirawat_mapper/io/usagi.py
thirawat_mapper/models/__init__.py
thirawat_mapper/models/bms_pooling.py
thirawat_mapper/models/embedder.py
thirawat_mapper/models/rag_llm.py
thirawat_mapper/models/rag_pipeline.py
thirawat_mapper/models/rag_prompt.py
thirawat_mapper/models/reranker.py
thirawat_mapper/scoring/__init__.py
thirawat_mapper/scoring/post_scorer.py
thirawat_mapper/utils/__init__.py
thirawat_mapper/utils/lancedb.py
thirawat_mapper/utils/text.py
thirawat_mapper-0.1.4.dist-info/METADATA
thirawat_mapper-0.1.4.dist-info/WHEEL
thirawat_mapper-0.1.4.dist-info/entry_points.txt
thirawat_mapper-0.1.4.dist-info/RECORD
