Metadata-Version: 2.4
Name: thirawat-mapper
Version: 0.1.4
Summary: Minimal indexing and inference toolkit for terminology mapping.
Project-URL: Repository, https://sidata.plus/projects/thirawat-mapper-beta
Project-URL: Issues, https://sidata.plus/support
Author-email: Natthawut Max Adulyanukosol <max@sidata.plus>
Requires-Python: >=3.11
Requires-Dist: datasets>=4.0
Requires-Dist: duckdb>=0.10
Requires-Dist: lance>=0.13
Requires-Dist: lancedb>=0.9
Requires-Dist: numpy>=1.24
Requires-Dist: openpyxl>=3.1.5
Requires-Dist: pandas>=2.0
Requires-Dist: protobuf>=4.25
Requires-Dist: pyarrow>=14.0
Requires-Dist: pydantic>=2.7
Requires-Dist: pylate>=1.3
Requires-Dist: rerankers>=0.7
Requires-Dist: rich>=13.7
Requires-Dist: sentence-transformers>=2.4
Requires-Dist: sentencepiece>=0.2.1
Requires-Dist: tiktoken>=0.7
Requires-Dist: torch>=2.2
Requires-Dist: tqdm>=4.66
Requires-Dist: transformers>=4.38
